cli.py
db.py
fields.py
info.py
main.py
time_helper.py
2adif-0.1.0.dist-info/LICENSE
2adif-0.1.0.dist-info/METADATA
2adif-0.1.0.dist-info/WHEEL
2adif-0.1.0.dist-info/entry_points.txt
2adif-0.1.0.dist-info/top_level.txt
2adif-0.1.0.dist-info/RECORD
