Metadata-Version: 2.2
Name: 2adif
Version: 0.1.0
Summary: Convert table to ADIF format.
Author: uiolee
Maintainer: uiolee
License: MPL 2.0
Project-URL: Homepage, https://github.com/uiolee/2adif
Project-URL: Repository, https://github.com/uiolee/2adif.git
Project-URL: Issues, https://github.com/uiolee/2adif/issues
Keywords: ADIF,csv,hamradio
Classifier: Development Status :: 4 - Beta
Classifier: Environment :: Console
Classifier: Intended Audience :: Developers
Classifier: Intended Audience :: End Users/Desktop
Classifier: Topic :: File Formats
Classifier: Topic :: Utilities
Classifier: License :: OSI Approved :: Mozilla Public License 2.0 (MPL 2.0)
Classifier: Natural Language :: English
Classifier: Operating System :: Microsoft :: Windows
Classifier: Operating System :: POSIX :: Linux
Classifier: Operating System :: MacOS
Classifier: Programming Language :: Python :: 3.11
License-File: LICENSE
Requires-Dist: Scrapy
